edaSQL.py
eda_SQL-0.0.1.dist-info/METADATA
eda_SQL-0.0.1.dist-info/WHEEL
eda_SQL-0.0.1.dist-info/top_level.txt
eda_SQL-0.0.1.dist-info/RECORD
